vg_bodypix/BodyPixPose.py
vg_bodypix/BodyPixPoseEstimator.py
vg_bodypix/__init__.py
vg_bodypix/vendor/AbstractModel.py
vg_bodypix/vendor/BodyPixModel.py
vg_bodypix/vendor/__init__.py
vg_bodypix/vendor/openvino_utils.py
vg_bodypix/vendor/types.py
vg_bodypix/vendor/utils.py
visiongraph_bodypix-0.1.0.dist-info/LICENSE
visiongraph_bodypix-0.1.0.dist-info/METADATA
visiongraph_bodypix-0.1.0.dist-info/WHEEL
visiongraph_bodypix-0.1.0.dist-info/top_level.txt
visiongraph_bodypix-0.1.0.dist-info/RECORD
